hausse/__init__.py
hausse/__main__.py
hausse/hausse.py
hausse/lib/__init__.py
hausse/lib/element.py
hausse/lib/plugin.py
hausse/lib/project.py
hausse/lib/selector.py
hausse/plugins/__init__.py
hausse/plugins/assets.py
hausse/plugins/csv_expand.py
hausse/plugins/data/__init__.py
hausse/plugins/data/markdown.py
hausse/plugins/elements/__init__.py
hausse/plugins/elements/collection.py
hausse/plugins/elements/drop.py
hausse/plugins/elements/index.py
hausse/plugins/elements/keep.py
hausse/plugins/elements/metadata.py
hausse/plugins/elements/relations.py
hausse/plugins/layout/__init__.py
hausse/plugins/layout/discover_partials.py
hausse/plugins/layout/handlebars.py
hausse/plugins/layout/layouts.py
hausse/plugins/metadata/__init__.py
hausse/plugins/metadata/metadata_markdown.py
hausse/utils/__init__.py
hausse/utils/constants.py
hausse/utils/functions.py
tests/__init__.py
tests/test_hausse.py
tests/plugins/__init__.py
tests/plugins/test_collections.py
tests/plugins/test_drop.py
tests/plugins/test_keep.py
tests/plugins/test_markdown.py
tests/plugins/test_metadata.py
hausse-0.3.0.dist-info/LICENSE
hausse-0.3.0.dist-info/METADATA
hausse-0.3.0.dist-info/WHEEL
hausse-0.3.0.dist-info/top_level.txt
hausse-0.3.0.dist-info/RECORD
