Metadata-Version: 2.1
Name: hausse
Version: 0.3.0
Summary: Plugin-based static project generator
Home-page: https://github.com/andrenasturas/hausse
Author: André Nasturas
Author-email: andre.nasturas@delfosia.net
License: UNKNOWN
Project-URL: Bug Tracker, https://github.com/andrenasturas/hausse/issues
Platform: UNKNOWN
Classifier: Programming Language :: Python :: 3
Classifier: License :: OSI Approved :: MIT License
Classifier: Operating System :: OS Independent
Requires-Python: >=3.9
License-File: LICENSE
